forkbuntu/__init__.py
forkbuntu/__main__.py
forkbuntu/logger.yml
forkbuntu/preseed.seed
forkbuntu/step.py
forkbuntu/apt-ftparchive/apt-ftparchive-deb.conf
forkbuntu/apt-ftparchive/apt-ftparchive-extras.conf
forkbuntu/apt-ftparchive/apt-ftparchive-udeb.conf
forkbuntu/apt-ftparchive/release.conf
forkbuntu/controllers/__init__.py
forkbuntu/controllers/base.py
forkbuntu/controllers/clean.py
forkbuntu/filesystem/etc/lsb-release
forkbuntu/iso/README.diskdefines
forkbuntu/iso/.disk/info
forkbuntu/iso/scripts/filesystem.sh
forkbuntu/iso/scripts/postinstall.sh
forkbuntu/iso/scripts/run_postinstall.sh
forkbuntu/isolinux/txt.cfg
forkbuntu/services/__init__.py
forkbuntu/services/cache.py
forkbuntu/services/clean.py
forkbuntu/services/configure.py
forkbuntu/services/extras.py
forkbuntu/services/filesystem.py
forkbuntu/services/gpg.py
forkbuntu/services/initrd.py
forkbuntu/services/iso.py
forkbuntu/services/setup.py
forkbuntu/services/util.py
forkbuntu/steps/__init__.py
forkbuntu/steps/build_keyring.py
forkbuntu/steps/clean.py
forkbuntu/steps/configure_filesystem.py
forkbuntu/steps/create_extras.py
forkbuntu/steps/initialize.py
forkbuntu/steps/load_config.py
forkbuntu/steps/merge_filesystem.py
forkbuntu/steps/merge_initrd.py
forkbuntu/steps/merge_iso.py
forkbuntu/steps/pack_filesystem.py
forkbuntu/steps/pack_initrd.py
forkbuntu/steps/pack_iso.py
forkbuntu/steps/sign_iso.py
forkbuntu/steps/unpack_filesystem.py
forkbuntu/steps/unpack_initrd.py
forkbuntu/steps/unpack_iso.py
forkbuntu-0.2.10.dist-info/METADATA
forkbuntu-0.2.10.dist-info/RECORD
forkbuntu-0.2.10.dist-info/WHEEL
forkbuntu-0.2.10.dist-info/entry_points.txt
forkbuntu-0.2.10.dist-info/top_level.txt
